Workbook

Sheet Master Dashboard
A1: CHINA SHIPMENT - FULLY AUTOMATED SETTLEMENT & CASH FLOW ENGINE
A4: Shipment Invoice No: | B4: 2025(SLLK)823 | D4: Total Shipment Units: | E4: 472 | G4: Base Budget USD Rate: | H4: 330
A5: Total China FOB Value ($): | B5: 206316.96 | D5: Customs, Tax & Clearing (LKR): | E5: 4991500 | G5: TOTAL CHINA LIABILITY (LKR): | H5: 73076097
A7: 1. LIVE EXECUTIVE FINANCIAL POSITION
A8: TOTAL CHINA LIABILITY | C8: TOTAL RECEIVED FROM GLOBAL | E8: TOTAL SETTLED TO CHINA | G8: OUR NET CASH CONTRIBUTED | I8: REMAINING DUE TO CHINA
A9: =H5 -> 73076097 | C9: ='Global Inflow Log'!E500 -> 15917478 | E9: ='China Outflow Log'!H500 -> 30534298 | I9: =A9-E9 -> 42541799
A12: 2. PARTNER LIABILITY & SETTLEMENT SHARE
A14: Partner Entity | B14: Operational Role / Settlement Responsibility | C14: Agreed Ratio | D14: Target Liability (LKR) | E14: Actual Paid / Handed Over (LKR) | F14: Remaining Due (LKR) | G14: Progress % | H14: Live Account Status
A15: Global Apparel Solutions | B15: Gives cash to Our Company | C15: 0.5 | D15: =$H$5*C15 -> 36538048 | E15: =C9 -> 15917478 | F15: =D15-E15 -> 20620570 | G15: =IF(D15>0, E15/D15, 0) -> 0.43564117 | H15: =IF(F15<=0, "✓ FULLY SETTLED TO US", "⚠ GLOBAL OWES US: " & TEXT(F15, "#,##0.00")) -> ⚠ GLOBAL OWES US: 20,620,570.30
A16: Our Company | B16: Direct Outflow Execution to China | C16: 0.5 | D16: =$H$5*C16 -> 36538048 | E16: =G9 -> 0 | F16: =D16-E16 -> 36538048 | G16: =IF(D16>0, E16/D16, 0) -> 0 | H16: =IF(F16<=0, "✓ OUR SHARE COMPLETED", "⏳ OUR SHARE PENDING: " & TEXT(F16, "#,##0.00")) -> ⏳ OUR SHARE PENDING: 36,538,048.40
A17: COMBINED PARTNERSHIP TOTAL | B17: 100.0% China Liability Settlement | C17: =SUM(C15:C16) -> 1 | D17: =SUM(D15:D16) -> 73076097 | E17: =SUM(E15:E16) -> 15917478 | F17: =SUM(F15:F16) -> 57158619 | G17: =IF(D17>0, E17/D17, 0) -> 0.21782058 | H17: =IF(I9<=0, "✓ 100% COMPLETE & SETTLED", "REMAINING TOTAL: " & TEXT(I9, "#,##0.00")) -> REMAINING TOTAL: 42,541,798.70
A20: 3. OVERSEAS FRIENDS & AGENTS RECONCILIATION SUMMARY
A22: Friend / Intermediary Name | B22: Country / Route | C22: Operating Currency | D22: Total Cash Given by Us (LKR) | E22: Total Settled to China (LKR Equiv) | F22: Net Balance (LKR) | G22: Current Settlement Status | H22: Action / Instructions
A23: Ashen | D23: ='Friend & Agent Settlement'!C15 -> 4300000 | E23: ='Friend & Agent Settlement'!G15 -> 4454800 | F23: ='Friend & Agent Settlement'!H15 -> -154800 | G23: ='Friend & Agent Settlement'!I15 -> We owe Friend | H23: =IF(F23>0, "Hold surplus for next tranche", IF(F23<0, "Api must pay balance to Ashen", "Settled")) -> Api must pay balance to Ashen
A24: Friend 2 (Korea) | B24: Korea | D24: ='Friend & Agent Settlement'!C32 -> 10109330 | E24: ='Friend & Agent Settlement'!G32 -> 10162020 | F24: ='Friend & Agent Settlement'!H32 -> -52690 | G24: We Owe Friend | H24: =IF(F24>0, "Surplus held for next batch", IF(F24<0, "Api must pay balance to friend", "Settled")) -> Api must pay balance to friend
A25: Direct Bank TT (Sri Lanka) | B25: Commercial / BOC / Sampath | C25: USD Wire | D25: 15917478 | E25: 15917478 | F25: 0 | G25: Settled Directly via TT | H25: Direct Supplier Wire Completed

Sheet Global Inflow Log
A1: GLOBAL APPAREL - INWARD FUNDS RECEIVED LOG
A4: Receipt ID | B4: Date Received | C4: Payment Method (Cheque / Bank Transfer / Cash) | D4: Reference / Cheque No / Account Details | E4: Amount Received in LKR | F4: Cumulative Received in LKR | G4: Allocation Status | H4: Remarks / Special Notes
A5: GLB-001 | B5: 46243 | E5: 15917478
A6: GLB-002
A7: GLB-003 | F7: =IF(OR(E7="",E7=0), "", IF(ISNUMBER(F6), F6+E7, E7)) | G7: =IF(OR(E7="",E7=0), "", "✓ Received & Logged")
A8: GLB-004 | F8: =IF(OR(E8="",E8=0), "", IF(ISNUMBER(F7), F7+E8, E8)) | G8: =IF(OR(E8="",E8=0), "", "✓ Received & Logged")
A9: GLB-005 | F9: =IF(OR(E9="",E9=0), "", IF(ISNUMBER(F8), F8+E9, E9)) | G9: =IF(OR(E9="",E9=0), "", "✓ Received & Logged")
A10: GLB-006 | F10: =IF(OR(E10="",E10=0), "", IF(ISNUMBER(F9), F9+E10, E10)) | G10: =IF(OR(E10="",E10=0), "", "✓ Received & Logged")
A11: GLB-007 | F11: =IF(OR(E11="",E11=0), "", IF(ISNUMBER(F10), F10+E11, E11)) | G11: =IF(OR(E11="",E11=0), "", "✓ Received & Logged")
A12: GLB-008 | F12: =IF(OR(E12="",E12=0), "", IF(ISNUMBER(F11), F11+E12, E12)) | G12: =IF(OR(E12="",E12=0), "", "✓ Received & Logged")
A13: GLB-009 | F13: =IF(OR(E13="",E13=0), "", IF(ISNUMBER(F12), F12+E13, E13)) | G13: =IF(OR(E13="",E13=0), "", "✓ Received & Logged")
A14: GLB-010 | F14: =IF(OR(E14="",E14=0), "", IF(ISNUMBER(F13), F13+E14, E14)) | G14: =IF(OR(E14="",E14=0), "", "✓ Received & Logged")
A15: GLB-011 | F15: =IF(OR(E15="",E15=0), "", IF(ISNUMBER(F14), F14+E15, E15)) | G15: =IF(OR(E15="",E15=0), "", "✓ Received & Logged")
A16: GLB-012 | F16: =IF(OR(E16="",E16=0), "", IF(ISNUMBER(F15), F15+E16, E16)) | G16: =IF(OR(E16="",E16=0), "", "✓ Received & Logged")
A17: GLB-013 | F17: =IF(OR(E17="",E17=0), "", IF(ISNUMBER(F16), F16+E17, E17)) | G17: =IF(OR(E17="",E17=0), "", "✓ Received & Logged")
A18: GLB-014 | F18: =IF(OR(E18="",E18=0), "", IF(ISNUMBER(F17), F17+E18, E18)) | G18: =IF(OR(E18="",E18=0), "", "✓ Received & Logged")
... A499: GLB-495 | F499: =IF(OR(E499="",E499=0), "", IF(ISNUMBER(F498), F498+E499, E499)) | G499: =IF(OR(E499="",E499=0), "", "✓ Received & Logged")
A500: TOTAL INWARD FUNDS RECEIVED FROM GLOBAL APPAREL / GLOBAL වෙතින් ලැබුණු මුළු එකතුව | E500: =SUM(E5:E499) -> 15917478 | F500: =MAX(F5:F499) -> 0

Sheet China Outflow Log
A1: CHINA SHIPMENT - OUTWARD SETTLEMENT LOG
A4: Trx ID | B4: Payment Date | C4: Settlement Route / Channel | D4: Intermediary / Bank Partner | E4: Currency Sent (RMB / USD / AED) | F4: Foreign Amount Sent | G4: Applied FX Rate (LKR) | H4: Total LKR Settled to China | I4: Cumulative Settled | J4: Source of Funds (Global / Api) | K4: Transaction Reference / Notes
A5: TRX-001 | B5: 46063 | C5: Ashen | D5: Ashen | E5: RMB | F5: 86000 | G5: 51.8 | H5: =IF(AND(ISNUMBER(F5),ISNUMBER(G5),F5>0,G5>0), ROUND(F5*G5, 2), "") -> 4454800 | I5: =IF(H5>0, H5, 0) -> 4454800
A6: TRX-002 | B6: 46032 | D6: Korea | E6: RMB | F6: 60000 | G6: 51.9 | H6: =SUM(G6*F6) -> 3114000 | I6: =IF(H6>0, H6, 0) -> 3114000
A7: TRX-003 | B7: 46032 | D7: Korea | E7: RMB | F7: 15000 | G7: 51.9 | H7: =IF(AND(ISNUMBER(F7),ISNUMBER(G7),F7>0,G7>0), ROUND(F7*G7, 2), "") -> 778500 | I7: =IF(H7>0, H7, 0) -> 778500
A8: TRX-004 | B8: 46032 | D8: Korea | E8: RMB | F8: 25000 | G8: 51.9 | H8: =IF(AND(ISNUMBER(F8),ISNUMBER(G8),F8>0,G8>0), ROUND(F8*G8, 2), "") -> 1297500 | I8: =IF(H8>0, H8, 0) -> 1297500
A9: TRX-005 | C9: TT | H9: 15917478 | I9: 15917478
A10: TRX-006 | D10: Korea | F10: 19800 | G10: 51.9 | H10: =SUM(G10*F10) -> 1027620 | I10: =SUM(H10*G10) -> 53333478
A11: TRX-007 | D11: Korea | F11: 76000 | G11: 51.9 | H11: =IF(AND(ISNUMBER(F11),ISNUMBER(G11),F11>0,G11>0), ROUND(F11*G11, 2), "") -> 3944400 | I11: =IF(AND(ISNUMBER(G11),ISNUMBER(H11),G11>0,H11>0), ROUND(G11*H11, 2), "") -> 204714360
A12: TRX-008 | H12: =IF(AND(ISNUMBER(F12),ISNUMBER(G12),F12>0,G12>0), ROUND(F12*G12, 2), "") | I12: =IF(OR(H12="",H12=0), "", IF(ISNUMBER(I11), I11+H12, H12))
A13: TRX-009 | H13: =IF(AND(ISNUMBER(F13),ISNUMBER(G13),F13>0,G13>0), ROUND(F13*G13, 2), "") | I13: =IF(OR(H13="",H13=0), "", IF(ISNUMBER(I12), I12+H13, H13))
A14: TRX-010 | H14: =IF(AND(ISNUMBER(F14),ISNUMBER(G14),F14>0,G14>0), ROUND(F14*G14, 2), "") | I14: =IF(OR(H14="",H14=0), "", IF(ISNUMBER(I13), I13+H14, H14))
A15: TRX-011 | H15: =IF(AND(ISNUMBER(F15),ISNUMBER(G15),F15>0,G15>0), ROUND(F15*G15, 2), "") | I15: =IF(OR(H15="",H15=0), "", IF(ISNUMBER(I14), I14+H15, H15))
A16: TRX-012 | H16: =IF(AND(ISNUMBER(F16),ISNUMBER(G16),F16>0,G16>0), ROUND(F16*G16, 2), "") | I16: =IF(OR(H16="",H16=0), "", IF(ISNUMBER(I15), I15+H16, H16))
A17: TRX-013 | H17: =IF(AND(ISNUMBER(F17),ISNUMBER(G17),F17>0,G17>0), ROUND(F17*G17, 2), "") | I17: =IF(OR(H17="",H17=0), "", IF(ISNUMBER(I16), I16+H17, H17))
A18: TRX-014 | H18: =IF(AND(ISNUMBER(F18),ISNUMBER(G18),F18>0,G18>0), ROUND(F18*G18, 2), "") | I18: =IF(OR(H18="",H18=0), "", IF(ISNUMBER(I17), I17+H18, H18))
A19: TRX-015 | H19: =IF(AND(ISNUMBER(F19),ISNUMBER(G19),F19>0,G19>0), ROUND(F19*G19, 2), "") | I19: =IF(OR(H19="",H19=0), "", IF(ISNUMBER(I18), I18+H19, H19))
A20: TRX-016 | H20: =IF(AND(ISNUMBER(F20),ISNUMBER(G20),F20>0,G20>0), ROUND(F20*G20, 2), "") | I20: =IF(OR(H20="",H20=0), "", IF(ISNUMBER(I19), I19+H20, H20))
A21: TRX-017 | H21: =IF(AND(ISNUMBER(F21),ISNUMBER(G21),F21>0,G21>0), ROUND(F21*G21, 2), "") | I21: =IF(OR(H21="",H21=0), "", IF(ISNUMBER(I20), I20+H21, H21))
A22: TRX-018 | H22: =IF(AND(ISNUMBER(F22),ISNUMBER(G22),F22>0,G22>0), ROUND(F22*G22, 2), "") | I22: =IF(OR(H22="",H22=0), "", IF(ISNUMBER(I21), I21+H22, H22))
A23: TRX-019 | H23: =IF(AND(ISNUMBER(F23),ISNUMBER(G23),F23>0,G23>0), ROUND(F23*G23, 2), "") | I23: =IF(OR(H23="",H23=0), "", IF(ISNUMBER(I22), I22+H23, H23))
... A499: TRX-495 | H499: =IF(AND(ISNUMBER(F499),ISNUMBER(G499),F499>0,G499>0), ROUND(F499*G499, 2), "") | I499: =IF(OR(H499="",H499=0), "", IF(ISNUMBER(I498), I498+H499, H499))
A500: TOTAL SETTLED TO CHINA / චීනයට ගෙවා අවසන් මුළු මුදල | F500: =SUM(F5:F499) -> 281800 | H500: =SUM(H5:H499) -> 30534298 | I500: =MAX(I5:I499) -> 204714360

Sheet Friend & Agent Settlement
A1: INTERMEDIARY & OVERSEAS FRIEND RECONCILIATION LEDGER
A2: Tracking cash given to friends vs foreign payments settled to China with dynamic rate-based auto calculation
A4: ★ INTERMEDIARY 1: ASHEN
A6: Date | B6: Description / Bank Reference | C6: Cash Given by Us (LKR) | D6: Foreign Curr | E6: Foreign Amount | F6: Applied FX Rate | G6: LKR Settled to China | H6: Difference LKR | I6: Balance Status | J6: Running Balance (LKR) | K6: Settlement Notes / Remarks
A7: 46063 | B7: BOC - Commercial Bank | C7: 4300000 | D7: RMB | E7: 86000 | F7: 51.8 | G7: =IF(AND(ISNUMBER(E7),ISNUMBER(F7),E7>0,F7>0), ROUND(E7*F7, 2), IF(E7>0, E7, 0)) -> 4454800 | H7: =C7-G7 -> -154800 | I7: We owe Friend | J7: =H7 -> -154800
G11: =IF(AND(ISNUMBER(E11),ISNUMBER(F11),E11>0,F11>0), ROUND(E11*F11, 2), "") | I11: =IF(H11="","", IF(H11>0, "Friend Holds Surplus (අපට ලැබිය යුතු)", IF(H11<0, "We Owe Friend (අප දිය යුතු)", "Balanced / සමබරයි"))) | J11: =IF(H11="","", IF(ISNUMBER(J10), J10+H11, H11))
G12: =IF(AND(ISNUMBER(E12),ISNUMBER(F12),E12>0,F12>0), ROUND(E12*F12, 2), "") | I12: =IF(H12="","", IF(H12>0, "Friend Holds Surplus (අපට ලැබිය යුතු)", IF(H12<0, "We Owe Friend (අප දිය යුතු)", "Balanced / සමබරයි"))) | J12: =IF(H12="","", IF(ISNUMBER(J11), J11+H12, H12))
G13: =IF(AND(ISNUMBER(E13),ISNUMBER(F13),E13>0,F13>0), ROUND(E13*F13, 2), "") | I13: =IF(H13="","", IF(H13>0, "Friend Holds Surplus (අපට ලැබිය යුතු)", IF(H13<0, "We Owe Friend (අප දිය යුතු)", "Balanced / සමබරයි"))) | J13: =IF(H13="","", IF(ISNUMBER(J12), J12+H13, H13))
G14: =IF(AND(ISNUMBER(E14),ISNUMBER(F14),E14>0,F14>0), ROUND(E14*F14, 2), "") | I14: =IF(H14="","", IF(H14>0, "Friend Holds Surplus (අපට ලැබිය යුතු)", IF(H14<0, "We Owe Friend (අප දිය යුතු)", "Balanced / සමබරයි"))) | J14: =IF(H14="","", IF(ISNUMBER(J13), J13+H14, H14))
A15: ASHEN ACCOUNT RECONCILIATION SUMMARY | C15: =SUM(C7:C14) -> 4300000 | E15: =SUM(E7:E14) -> 86000 | G15: =SUM(G7:G14) -> 4454800 | H15: =C15-G15 -> -154800 | I15: We owe Friend | J15: =H15 -> -154800
A17: ★ INTERMEDIARY 2: FRIEND 2 (Korea)
A19: Date | B19: Description / Bank Reference | C19: Cash Given by Us (LKR) | D19: Foreign Curr | E19: Foreign Amount | F19: Applied FX Rate | G19: LKR Settled to China | H19: Difference LKR | I19: Balance Status | J19: Running Balance (LKR) | K19: Settlement Notes / Remarks
A20: 46032 | B20: DFCC - BOC | C20: 2500000 | D20: RMB | E20: 60000 | F20: 51.9 | G20: =SUM(F20*E20) -> 3114000 | I20: We owe Friend
A21: 46032 | B21: BOC - HNB | C21: 2450000 | D21: RMB | E21: 15000 | F21: 51.9 | G21: =IF(AND(ISNUMBER(E21),ISNUMBER(F21),E21>0,F21>0), ROUND(E21*F21, 2), "") -> 778500 | I21: =IF(H21="","", IF(H21>0, "Friend Holds Surplus (අපට ලැබිය යුතු)", IF(H21<0, "We Owe Friend (අප දිය යුතු)", "Balanced / සමබරයි"))) | J21: =IF(H21="","", IF(ISNUMBER(J20), J20+H21, H21))
A22: 46063 | B22: BOC - HNB | C22: 40000 | D22: RMB | E22: 25000 | F22: 51.9 | G22: =IF(AND(ISNUMBER(E22),ISNUMBER(F22),E22>0,F22>0), ROUND(E22*F22, 2), "") -> 1297500 | I22: =IF(H22="","", IF(H22>0, "Friend Holds Surplus (අපට ලැබිය යුතු)", IF(H22<0, "We Owe Friend (අප දිය යුතු)", "Balanced / සමබරයි"))) | J22: =IF(H22="","", IF(ISNUMBER(J21), J21+H22, H22))
A23: 46063 | C23: 10000 | D23: RMB | G23: =IF(AND(ISNUMBER(E23),ISNUMBER(F23),E23>0,F23>0), ROUND(E23*F23, 2), "") | I23: =IF(H23="","", IF(H23>0, "Friend Holds Surplus (අපට ලැබිය යුතු)", IF(H23<0, "We Owe Friend (අප දිය යුතු)", "Balanced / සමබරයි"))) | J23: =IF(H23="","", IF(ISNUMBER(J22), J22+H23, H23))
A24: 46091 | B24: BOC-Seylan | C24: 1000000 | D24: RMB | E24: 19800 | F24: 51.9 | G24: =SUM(F24*E24) -> 1027620
A25: 46122 | B25: Boc-Sampath | C25: 3919330 | D25: RMB | E25: 76000 | F25: 51.9 | G25: =IF(AND(ISNUMBER(E25),ISNUMBER(F25),E25>0,F25>0), ROUND(E25*F25, 2), "") -> 3944400 | J25: =IF(H25="","", IF(ISNUMBER(J17), J17+H25, H25))
A26: 46122 | C26: 190000
G31: =IF(AND(ISNUMBER(E31),ISNUMBER(F31),E31>0,F31>0), ROUND(E31*F31, 2), "") | J31: =IF(H31="","", IF(ISNUMBER(J23), J23+H31, H31))
A32: DUBAI FRIEND ACCOUNT RECONCILIATION | C32: =SUM(C20:C31) -> 10109330 | E32: =SUM(E20:E31) -> 195800 | G32: =SUM(G20:G31) -> 10162020 | H32: =C32-G32 -> -52690 | J32: =H32 -> -52690
A34: ★ DIRECT BANK TRANSFERS
A36: Date | B36: Description / Bank Reference | C36: Cash Given by Us (LKR) | D36: Foreign Curr | E36: Foreign Amount | F36: Applied FX Rate | G36: LKR Settled to China | H36: Difference LKR | I36: Balance Status | J36: Running Balance (LKR) | K36: Settlement Notes / Remarks
A37: 2026-09-05 | B37: Global Apparel - Commercial Bank USD TT
G40: =IF(AND(ISNUMBER(E40),ISNUMBER(F40),E40>0,F40>0), ROUND(E40*F40, 2), "") | I40: =IF(H40="","", IF(H40>0, "Friend Holds Surplus (අපට ලැබිය යුතු)", IF(H40<0, "We Owe Friend (අප දිය යුතු)", "Balanced / සමබරයි"))) | J40: =IF(H40="","", IF(ISNUMBER(J39), J39+H40, H40))
G41: =IF(AND(ISNUMBER(E41),ISNUMBER(F41),E41>0,F41>0), ROUND(E41*F41, 2), "") | I41: =IF(H41="","", IF(H41>0, "Friend Holds Surplus (අපට ලැබිය යුතු)", IF(H41<0, "We Owe Friend (අප දිය යුතු)", "Balanced / සමබරයි"))) | J41: =IF(H41="","", IF(ISNUMBER(J40), J40+H41, H41))
A42: DIRECT BANK TRANSFERS TOTAL | C42: =SUM(C37:C41) -> 0 | E42: =SUM(E37:E41) -> 0 | G42: =SUM(G37:G41) -> 0 | H42: =C42-G42 -> 0 | J42: =H42 -> 0
